caqtus_devices/motorized_stages/thorlabs_ell14/__init__.py
caqtus_devices/motorized_stages/thorlabs_ell14/_compiler.py
caqtus_devices/motorized_stages/thorlabs_ell14/_controller.py
caqtus_devices/motorized_stages/thorlabs_ell14/_extension.py
caqtus_devices/motorized_stages/thorlabs_ell14/_proxy.py
caqtus_devices/motorized_stages/thorlabs_ell14/py.typed
caqtus_devices/motorized_stages/thorlabs_ell14/configuration/__init__.py
caqtus_devices/motorized_stages/thorlabs_ell14/configuration/ell14_configuration.py
caqtus_devices/motorized_stages/thorlabs_ell14/configuration_editor/__init__.py
caqtus_devices/motorized_stages/thorlabs_ell14/configuration_editor/elliptec_ell14_config_editor.py
caqtus_devices/motorized_stages/thorlabs_ell14/runtime/__init__.py
caqtus_devices/motorized_stages/thorlabs_ell14/runtime/elliptec_ell14.py
caqtus_devices_thorlabs_ell14-1.0.0.dist-info/METADATA
caqtus_devices_thorlabs_ell14-1.0.0.dist-info/WHEEL
caqtus_devices_thorlabs_ell14-1.0.0.dist-info/licenses/license.md
caqtus_devices_thorlabs_ell14-1.0.0.dist-info/RECORD
