Metadata-Version: 2.4
Name: caqtus-devices-thorlabs-ell14
Version: 1.0.0
Summary: Contains extension code for caqtus framework for motorized stage Thorlabs ELL14
Author-email: light-scattering-io <lecaqtus66@gmail.com>
License: Copyright 2024 Université Paris-Saclay
License-File: license.md
Requires-Python: >=3.12
Requires-Dist: caqtus-suite>=6.18.1
Requires-Dist: pyserial>=3.5
Requires-Dist: thorlabs-elliptec>=1.2.0
